alltwobitsequencedetector.v
module alltwobitsequencedetector(x,s,clk,rst,y,NS);
input x,clk,rst;
input [1:0]s;
output reg y;
wire [1:0]s1,s2,s3;
output reg [1:0] NS;
assign s1 = 2'b00;
assign s2 = 2'b01;
assign s3 = 2'b10;
initial begin
        y = 1'b0;
end
always @(posedge clk)begin
        if(rst)begin
                NS = s1;
                y = 1'b0;
        end else begin
                if((x==s[1]) && (NS==s1)) begin
                        NS = s2;
                        y = 1'b0;
                end else if((x==(!s[1])) && (NS==s1))begin
                        NS = s1;
                        y = 1'b0;
                end else if((x==s[1]) && (NS==s3))begin
                        NS = s2;
                        y = 1'b0;
                end else if((x==(!s[1])) && (NS==s3))begin
                        NS = s1;
                        y = 1'b0;
                end else if(x==s[0]) begin
                        NS = s3;
                        y = 1'b1;
                end else begin
                        NS = s1;
                        y = 1'b0;
                end
        end
end
endmodule

alltwobitsequencedetector_tb.v
`timescale 1ns / 1ps
module alltwobitsequencedetector_tb;
reg clk,rst,x;
reg [1:0] s;
wire y;
wire [1:0] NS;
alltwobitsequencedetector a1(x,s,clk,rst,y,NS);
initial begin
clk=0;
end
always #5 clk=~clk;
initial begin
$dumpfile("dump.vcd");
$dumpvars(0, alltwobitsequencedetector_tb);
$monitor("at time %t: clk=%b rst=%b s=%b x=%b y=%b NS=%b",$time,clk,rst,s,x,y,NS);
                rst = 1'b1; s = 2'b00; x = 1'b1; #10;
                rst = 1'b0; s = 2'b00; x = 1'b1; #10;
                rst = 1'b0; s = 2'b00; x = 1'b1; #10;
                rst = 1'b0; s = 2'b00; x = 1'b0; #10;
                rst = 1'b0; s = 2'b00; x = 1'b0; #10;
                rst = 1'b0; s = 2'b00; x = 1'b0; #10;
                rst = 1'b0; s = 2'b00; x = 1'b1; #10;
                rst = 1'b0; s = 2'b00; x = 1'b0; #10;
                rst = 1'b0; s = 2'b00; x = 1'b1; #10;

                rst = 1'b1; s = 2'b01; x = 1'b1; #10;
                rst = 1'b0; s = 2'b01; x = 1'b1; #10;
                rst = 1'b0; s = 2'b01; x = 1'b1; #10;
                rst = 1'b0; s = 2'b01; x = 1'b0; #10;
                rst = 1'b0; s = 2'b01; x = 1'b0; #10;
                rst = 1'b0; s = 2'b01; x = 1'b0; #10;
                rst = 1'b0; s = 2'b01; x = 1'b1; #10;
                rst = 1'b0; s = 2'b01; x = 1'b0; #10;
                rst = 1'b0; s = 2'b01; x = 1'b1; #10;

                rst = 1'b1; s = 2'b10; x = 1'b1; #10;
                rst = 1'b0; s = 2'b10; x = 1'b1; #10;
                rst = 1'b0; s = 2'b10; x = 1'b1; #10;
                rst = 1'b0; s = 2'b10; x = 1'b0; #10;
                rst = 1'b0; s = 2'b10; x = 1'b0; #10;
                rst = 1'b0; s = 2'b10; x = 1'b0; #10;
                rst = 1'b0; s = 2'b10; x = 1'b1; #10;
                rst = 1'b0; s = 2'b10; x = 1'b0; #10;
                rst = 1'b0; s = 2'b10; x = 1'b1; #10;

                rst = 1'b1; s = 2'b11; x = 1'b1; #10;
                rst = 1'b0; s = 2'b11; x = 1'b1; #10;
                rst = 1'b0; s = 2'b11; x = 1'b1; #10;
                rst = 1'b0; s = 2'b11; x = 1'b0; #10;
                rst = 1'b0; s = 2'b11; x = 1'b0; #10;
                rst = 1'b0; s = 2'b11; x = 1'b0; #10;
                rst = 1'b0; s = 2'b11; x = 1'b1; #10;
                rst = 1'b0; s = 2'b11; x = 1'b0; #10;
                rst = 1'b0; s = 2'b11; x = 1'b1; #10;
                
        $finish;
end
endmodule

dump.vcd
$date
	Mon Jun 29 00:24:28 2026
$end
$version
	Icarus Verilog
$end
$timescale
	1ps
$end
$scope module alltwobitsequencedetector_tb $end
$var wire 1 ! y $end
$var wire 2 " NS [1:0] $end
$var reg 1 # clk $end
$var reg 1 $ rst $end
$var reg 2 % s [1:0] $end
$var reg 1 & x $end
$scope module a1 $end
$var wire 1 # clk $end
$var wire 1 $ rst $end
$var wire 2 ' s [1:0] $end
$var wire 2 ( s1 [1:0] $end
$var wire 2 ) s2 [1:0] $end
$var wire 2 * s3 [1:0] $end
$var wire 1 & x $end
$var reg 2 + NS [1:0] $end
$var reg 1 ! y $end
$upscope $end
$upscope $end
$enddefinitions $end
$comment Show the parameter values. $end
$dumpall
$end
#0
$dumpvars
bx +
b10 *
b1 )
b0 (
b0 '
1&
b0 %
1$
0#
bx "
0!
$end
#5000
b0 "
b0 +
1#
#10000
0#
0$
#15000
1#
#20000
0#
#25000
1#
#30000
0#
0&
#35000
b1 "
b1 +
1#
#40000
0#
#45000
1!
b10 "
b10 +
1#
#50000
0#
#55000
0!
b1 "
b1 +
1#
#60000
0#
1&
#65000
b0 "
b0 +
1#
#70000
0#
0&
#75000
b1 "
b1 +
1#
#80000
0#
1&
#85000
b0 "
b0 +
1#
#90000
0#
b1 %
b1 '
1$
#95000
1#
#100000
0#
0$
#105000
1#
#110000
0#
#115000
1#
#120000
0#
0&
#125000
b1 "
b1 +
1#
#130000
0#
#135000
b0 "
b0 +
1#
#140000
0#
#145000
b1 "
b1 +
1#
#150000
0#
1&
#155000
1!
b10 "
b10 +
1#
#160000
0#
0&
#165000
0!
b1 "
b1 +
1#
#170000
0#
1&
#175000
1!
b10 "
b10 +
1#
#180000
0#
b10 %
b10 '
1$
#185000
0!
b0 "
b0 +
1#
#190000
0#
0$
#195000
b1 "
b1 +
1#
#200000
0#
#205000
b0 "
b0 +
1#
#210000
0#
0&
#215000
1#
#220000
0#
#225000
1#
#230000
0#
#235000
1#
#240000
0#
1&
#245000
b1 "
b1 +
1#
#250000
0#
0&
#255000
1!
b10 "
b10 +
1#
#260000
0#
1&
#265000
0!
b1 "
b1 +
1#
#270000
0#
b11 %
b11 '
1$
#275000
b0 "
b0 +
1#
#280000
0#
0$
#285000
b1 "
b1 +
1#
#290000
0#
#295000
1!
b10 "
b10 +
1#
#300000
0#
0&
#305000
0!
b0 "
b0 +
1#
#310000
0#
#315000
1#
#320000
0#
#325000
1#
#330000
0#
1&
#335000
b1 "
b1 +
1#
#340000
0#
0&
#345000
b0 "
b0 +
1#
#350000
0#
1&
#355000
b1 "
b1 +
1#
